{
  "$schema": "https://raw.githubusercontent.com/spdx/spdx-spec/v2.2.1/schemas/spdx-schema.json",
  "spdxVersion": "SPDX-2.2",
  "dataLicense": "CC0-1.0",
  "SPDXID": "SPDXRef-DOCUMENT",
  "documentNamespace": "https://spdx.org/spdxdocs/azure-security-attestation-cpp-x64-windows-1.2.0-beta.1-4ef48d46-9031-4ca7-b5ad-a3db4c66292d",
  "name": "azure-security-attestation-cpp:x64-windows@1.2.0-beta.1 02623f4edb19d02bbdaca08cb120e4e68d936778b5ad35cc7ac29da877342d28",
  "creationInfo": {
    "creators": [
      "Tool: vcpkg-2025-11-19-da1f056dc0775ac651bea7e3fbbf4066146a55f3"
    ],
    "created": "2026-06-24T23:10:42Z"
  },
  "relationships": [
    {
      "spdxElementId": "SPDXRef-port",
      "relationshipType": "GENERATES",
      "relatedSpdxElement": "SPDXRef-binary"
    },
    {
      "spdxElementId": "SPDXRef-port",
      "relationshipType": "CONTAINS",
      "relatedSpdxElement": "SPDXRef-port-file-0"
    },
    {
      "spdxElementId": "SPDXRef-port",
      "relationshipType": "CONTAINS",
      "relatedSpdxElement": "SPDXRef-port-file-1"
    },
    {
      "spdxElementId": "SPDXRef-port-file-1",
      "relationshipType": "DEPENDENCY_MANIFEST_OF",
      "relatedSpdxElement": "SPDXRef-port"
    },
    {
      "spdxElementId": "SPDXRef-binary",
      "relationshipType": "CONTAINS",
      "relatedSpdxElement": "SPDXRef-binary-file-0"
    },
    {
      "spdxElementId": "SPDXRef-binary",
      "relationshipType": "CONTAINS",
      "relatedSpdxElement": "SPDXRef-binary-file-1"
    },
    {
      "spdxElementId": "SPDXRef-binary",
      "relationshipType": "CONTAINS",
      "relatedSpdxElement": "SPDXRef-binary-file-2"
    },
    {
      "spdxElementId": "SPDXRef-binary",
      "relationshipType": "CONTAINS",
      "relatedSpdxElement": "SPDXRef-binary-file-3"
    },
    {
      "spdxElementId": "SPDXRef-binary",
      "relationshipType": "CONTAINS",
      "relatedSpdxElement": "SPDXRef-binary-file-4"
    },
    {
      "spdxElementId": "SPDXRef-binary",
      "relationshipType": "CONTAINS",
      "relatedSpdxElement": "SPDXRef-binary-file-5"
    },
    {
      "spdxElementId": "SPDXRef-binary",
      "relationshipType": "CONTAINS",
      "relatedSpdxElement": "SPDXRef-binary-file-6"
    },
    {
      "spdxElementId": "SPDXRef-binary",
      "relationshipType": "CONTAINS",
      "relatedSpdxElement": "SPDXRef-binary-file-7"
    },
    {
      "spdxElementId": "SPDXRef-binary",
      "relationshipType": "CONTAINS",
      "relatedSpdxElement": "SPDXRef-binary-file-8"
    },
    {
      "spdxElementId": "SPDXRef-binary",
      "relationshipType": "CONTAINS",
      "relatedSpdxElement": "SPDXRef-binary-file-9"
    },
    {
      "spdxElementId": "SPDXRef-binary",
      "relationshipType": "CONTAINS",
      "relatedSpdxElement": "SPDXRef-binary-file-10"
    },
    {
      "spdxElementId": "SPDXRef-binary",
      "relationshipType": "CONTAINS",
      "relatedSpdxElement": "SPDXRef-binary-file-11"
    },
    {
      "spdxElementId": "SPDXRef-binary",
      "relationshipType": "CONTAINS",
      "relatedSpdxElement": "SPDXRef-binary-file-12"
    },
    {
      "spdxElementId": "SPDXRef-binary",
      "relationshipType": "CONTAINS",
      "relatedSpdxElement": "SPDXRef-binary-file-13"
    },
    {
      "spdxElementId": "SPDXRef-binary",
      "relationshipType": "CONTAINS",
      "relatedSpdxElement": "SPDXRef-binary-file-14"
    },
    {
      "spdxElementId": "SPDXRef-binary",
      "relationshipType": "CONTAINS",
      "relatedSpdxElement": "SPDXRef-binary-file-15"
    },
    {
      "spdxElementId": "SPDXRef-binary",
      "relationshipType": "CONTAINS",
      "relatedSpdxElement": "SPDXRef-binary-file-16"
    },
    {
      "spdxElementId": "SPDXRef-binary",
      "relationshipType": "CONTAINS",
      "relatedSpdxElement": "SPDXRef-binary-file-17"
    },
    {
      "spdxElementId": "SPDXRef-binary",
      "relationshipType": "CONTAINS",
      "relatedSpdxElement": "SPDXRef-binary-file-18"
    },
    {
      "spdxElementId": "SPDXRef-binary",
      "relationshipType": "CONTAINS",
      "relatedSpdxElement": "SPDXRef-binary-file-19"
    }
  ],
  "packages": [
    {
      "name": "azure-security-attestation-cpp",
      "SPDXID": "SPDXRef-port",
      "versionInfo": "1.2.0-beta.1",
      "downloadLocation": "NOASSERTION",
      "homepage": "https://github.com/Azure/azure-sdk-for-cpp/tree/main/sdk/attestation/azure-security-attestation",
      "licenseConcluded": "MIT",
      "licenseDeclared": "NOASSERTION",
      "copyrightText": "NOASSERTION",
      "description": "Microsoft Azure Attestation Service SDK for C++\nThis library provides API access to the Microsoft Azure Attestation service.\nLocal-source overlay port: builds the working tree instead of a published release.",
      "comment": "This is the port (recipe) consumed by vcpkg."
    },
    {
      "name": "azure-security-attestation-cpp:x64-windows",
      "SPDXID": "SPDXRef-binary",
      "versionInfo": "02623f4edb19d02bbdaca08cb120e4e68d936778b5ad35cc7ac29da877342d28",
      "downloadLocation": "NONE",
      "licenseConcluded": "MIT",
      "licenseDeclared": "NOASSERTION",
      "copyrightText": "NOASSERTION",
      "comment": "This is a binary package built by vcpkg."
    }
  ],
  "files": [
    {
      "fileName": "./portfile.cmake",
      "SPDXID": "SPDXRef-port-file-0",
      "checksums": [
        {
          "algorithm": "SHA256",
          "checksumValue": "e8da62b82594b24c7f4a4b259d76ccf390861d0b01bb6ccf17c4302d50dd7af3"
        }
      ],
      "licenseConcluded": "NOASSERTION",
      "copyrightText": "NOASSERTION"
    },
    {
      "fileName": "./vcpkg.json",
      "SPDXID": "SPDXRef-port-file-1",
      "checksums": [
        {
          "algorithm": "SHA256",
          "checksumValue": "439f95f0f558a14b36fa9cff6c030948c54d56f1d2b2d1e32672bf3f90d0f02e"
        }
      ],
      "licenseConcluded": "NOASSERTION",
      "copyrightText": "NOASSERTION"
    },
    {
      "fileName": "./bin/azure-security-attestation.dll",
      "SPDXID": "SPDXRef-binary-file-0",
      "checksums": [
        {
          "algorithm": "SHA256",
          "checksumValue": "cb9e0941ed4475441324316ac1382df2881c991f1e4d1cad3aa24c488d4accee"
        }
      ],
      "licenseConcluded": "NOASSERTION",
      "copyrightText": "NOASSERTION"
    },
    {
      "fileName": "./bin/azure-security-attestation.pdb",
      "SPDXID": "SPDXRef-binary-file-1",
      "checksums": [
        {
          "algorithm": "SHA256",
          "checksumValue": "a107d3aae9d60a7e87524a73abec5accf462f03e9238c0f1895df61f056c333b"
        }
      ],
      "licenseConcluded": "NOASSERTION",
      "copyrightText": "NOASSERTION"
    },
    {
      "fileName": "./BUILD_INFO",
      "SPDXID": "SPDXRef-binary-file-2",
      "checksums": [
        {
          "algorithm": "SHA256",
          "checksumValue": "5e7f821ab4eb804deb535baa7b41edca682d0303cf21a91908c98d5c9a7dcf4d"
        }
      ],
      "licenseConcluded": "NOASSERTION",
      "copyrightText": "NOASSERTION"
    },
    {
      "fileName": "./debug/bin/azure-security-attestation.dll",
      "SPDXID": "SPDXRef-binary-file-3",
      "checksums": [
        {
          "algorithm": "SHA256",
          "checksumValue": "a6ae198183227f19b9e1fdd8d9a8a6a07c3710c237b6cd8b02cdf4ea6cd18f52"
        }
      ],
      "licenseConcluded": "NOASSERTION",
      "copyrightText": "NOASSERTION"
    },
    {
      "fileName": "./debug/bin/azure-security-attestation.pdb",
      "SPDXID": "SPDXRef-binary-file-4",
      "checksums": [
        {
          "algorithm": "SHA256",
          "checksumValue": "b758b21a4d2b2f8289dc7b460f3d41b545a11be051fcbfb006b4124dd39b6c06"
        }
      ],
      "licenseConcluded": "NOASSERTION",
      "copyrightText": "NOASSERTION"
    },
    {
      "fileName": "./debug/lib/azure-security-attestation.lib",
      "SPDXID": "SPDXRef-binary-file-5",
      "checksums": [
        {
          "algorithm": "SHA256",
          "checksumValue": "fe05aadbd69f3e8603bc44d28cf10c50e1b980ab3b32c30fc59ccf47afd2af46"
        }
      ],
      "licenseConcluded": "NOASSERTION",
      "copyrightText": "NOASSERTION"
    },
    {
      "fileName": "./include/azure/attestation/attestation_administration_client.hpp",
      "SPDXID": "SPDXRef-binary-file-6",
      "checksums": [
        {
          "algorithm": "SHA256",
          "checksumValue": "b80d273712ef0b8ebc6ca1686c3cefadbe9500658fd92d052a02444189650b15"
        }
      ],
      "licenseConcluded": "NOASSERTION",
      "copyrightText": "NOASSERTION"
    },
    {
      "fileName": "./include/azure/attestation/attestation_client.hpp",
      "SPDXID": "SPDXRef-binary-file-7",
      "checksums": [
        {
          "algorithm": "SHA256",
          "checksumValue": "b68cb1229cc9a57c4e261ccdc668248ac1b108de6e3aa58dead599ec86e6e299"
        }
      ],
      "licenseConcluded": "NOASSERTION",
      "copyrightText": "NOASSERTION"
    },
    {
      "fileName": "./include/azure/attestation/attestation_client_models.hpp",
      "SPDXID": "SPDXRef-binary-file-8",
      "checksums": [
        {
          "algorithm": "SHA256",
          "checksumValue": "9ec10e123de9916d77468a58d151c89dd8d211e1c531db25bd836e9d55dddc74"
        }
      ],
      "licenseConcluded": "NOASSERTION",
      "copyrightText": "NOASSERTION"
    },
    {
      "fileName": "./include/azure/attestation/attestation_client_options.hpp",
      "SPDXID": "SPDXRef-binary-file-9",
      "checksums": [
        {
          "algorithm": "SHA256",
          "checksumValue": "848ccbe59a79122f57d7987adeed683fd210ae4d7792f8737f9a3af2755f993d"
        }
      ],
      "licenseConcluded": "NOASSERTION",
      "copyrightText": "NOASSERTION"
    },
    {
      "fileName": "./include/azure/attestation/dll_import_export.hpp",
      "SPDXID": "SPDXRef-binary-file-10",
      "checksums": [
        {
          "algorithm": "SHA256",
          "checksumValue": "52e44d1a2418bc99b053237cac4e3b1663bbceefe9558403d34178281d1cf265"
        }
      ],
      "licenseConcluded": "NOASSERTION",
      "copyrightText": "NOASSERTION"
    },
    {
      "fileName": "./include/azure/attestation/rtti.hpp",
      "SPDXID": "SPDXRef-binary-file-11",
      "checksums": [
        {
          "algorithm": "SHA256",
          "checksumValue": "c078112683c26072a35eb4ba062cfce28ad6b44a4417ac05eec8458c18208db8"
        }
      ],
      "licenseConcluded": "NOASSERTION",
      "copyrightText": "NOASSERTION"
    },
    {
      "fileName": "./include/azure/attestation.hpp",
      "SPDXID": "SPDXRef-binary-file-12",
      "checksums": [
        {
          "algorithm": "SHA256",
          "checksumValue": "1733e9614c4994a038e37aefa7c56e3e281d88ce12f9ae11958af685a7f896b1"
        }
      ],
      "licenseConcluded": "NOASSERTION",
      "copyrightText": "NOASSERTION"
    },
    {
      "fileName": "./lib/azure-security-attestation.lib",
      "SPDXID": "SPDXRef-binary-file-13",
      "checksums": [
        {
          "algorithm": "SHA256",
          "checksumValue": "748fd852b20aee3d344a5f208a37de79404271590893d79efdc52becaa4e3bae"
        }
      ],
      "licenseConcluded": "NOASSERTION",
      "copyrightText": "NOASSERTION"
    },
    {
      "fileName": "./share/azure-security-attestation-cpp/azure-security-attestation-cppConfig.cmake",
      "SPDXID": "SPDXRef-binary-file-14",
      "checksums": [
        {
          "algorithm": "SHA256",
          "checksumValue": "86172dfc7d129e7b289459a19c34bd2f70710606000483ed135a17a65a636eed"
        }
      ],
      "licenseConcluded": "NOASSERTION",
      "copyrightText": "NOASSERTION"
    },
    {
      "fileName": "./share/azure-security-attestation-cpp/azure-security-attestation-cppConfigVersion.cmake",
      "SPDXID": "SPDXRef-binary-file-15",
      "checksums": [
        {
          "algorithm": "SHA256",
          "checksumValue": "7271e32bee76e25b61793816e30f9ab416cdd528140b987998cd33b0d8eb61ca"
        }
      ],
      "licenseConcluded": "NOASSERTION",
      "copyrightText": "NOASSERTION"
    },
    {
      "fileName": "./share/azure-security-attestation-cpp/azure-security-attestation-cppTargets-debug.cmake",
      "SPDXID": "SPDXRef-binary-file-16",
      "checksums": [
        {
          "algorithm": "SHA256",
          "checksumValue": "be3d43dc3130f8b53b16132b947e347c3323ca8d00bd65b7ffeef7274e864fc9"
        }
      ],
      "licenseConcluded": "NOASSERTION",
      "copyrightText": "NOASSERTION"
    },
    {
      "fileName": "./share/azure-security-attestation-cpp/azure-security-attestation-cppTargets-release.cmake",
      "SPDXID": "SPDXRef-binary-file-17",
      "checksums": [
        {
          "algorithm": "SHA256",
          "checksumValue": "8966d533a5e651d03f8aae042723f7b247815314a9f9d921efe7b8d2a86e6c21"
        }
      ],
      "licenseConcluded": "NOASSERTION",
      "copyrightText": "NOASSERTION"
    },
    {
      "fileName": "./share/azure-security-attestation-cpp/azure-security-attestation-cppTargets.cmake",
      "SPDXID": "SPDXRef-binary-file-18",
      "checksums": [
        {
          "algorithm": "SHA256",
          "checksumValue": "db70d4130ded4512bf5e809d8dc7940cb00834b4995af22f20a2f20b101751aa"
        }
      ],
      "licenseConcluded": "NOASSERTION",
      "copyrightText": "NOASSERTION"
    },
    {
      "fileName": "./share/azure-security-attestation-cpp/copyright",
      "SPDXID": "SPDXRef-binary-file-19",
      "checksums": [
        {
          "algorithm": "SHA256",
          "checksumValue": "9906940f61b1f0b533fa7d99baf55178b2808fbe113ea51dfbfad8572ccd5f2b"
        }
      ],
      "licenseConcluded": "NOASSERTION",
      "copyrightText": "NOASSERTION"
    }
  ]
}
